melodycraftWS/__init__.py
melodycraftWS/client/__init__.py
melodycraftWS/client/melody_craft_client.py
melodycraftWS/server/__init__.py
melodycraftWS/server/melody_craft_server.py
melodycraftWS/server/melody_generation.py
MelodyCraftWS-0.2.8.dist-info/LICENSE
MelodyCraftWS-0.2.8.dist-info/METADATA
MelodyCraftWS-0.2.8.dist-info/WHEEL
MelodyCraftWS-0.2.8.dist-info/dependency_links.txt
MelodyCraftWS-0.2.8.dist-info/top_level.txt
MelodyCraftWS-0.2.8.dist-info/RECORD
