Metadata-Version: 2.1
Name: MelodyCraftWS
Version: 0.2.8
Summary: 🎶 Transform text into beautiful melodies and stream real-time WebSockets to clients! 🚀
Home-page: https://github.com/sergio11/melodycraftWS
Author: Sergio Sánchez Sánchez
Author-email: dreamsoftware92@gmail.com
Keywords: music,text,WebSocket,melody
Classifier: Development Status :: 4 - Beta
Classifier: Intended Audience :: Developers
Classifier: License :: OSI Approved :: MIT License
Classifier: Programming Language :: Python :: 3
Classifier: Programming Language :: Python :: 3.7
Classifier: Programming Language :: Python :: 3.8
Classifier: Programming Language :: Python :: 3.9
Classifier: Programming Language :: Python :: 3.10
Requires-Python: >=3.7, <4
License-File: LICENSE
Requires-Dist: Flask (==3.0.0)
Requires-Dist: Flask-SocketIO (==5.3.6)
Requires-Dist: audiocraft (==1.0.0)
